{
    "DoNotUseThis": [
        {
            "Index": 1,
            "DefaultCondition": true
        },
        {
            "Index": 3,
            "DefaultCondition": true
        },
        {
            "Index": 4,
            "Type": 2
        },
        {
            "Index": 5,
            "Type": 2
        },
        {
            "Index": 6,
            "Type": 2
        },
        {
            "Index": 7,
            "Type": 2
        },
        {
            "Index": 8,
            "Type": 2
        },
        {
            "Index": 9,
            "Type": 1,
            "GuildSiegeDataIndex": 3
        },
        {
            "Index": 10,
            "Type": 1,
            "GuildSiegeDataIndex": 5
        },
        {
            "Index": 11,
            "Type": 1,
            "GuildSiegeDataIndex": 2
        },
        {
            "Index": 12,
            "Type": 1,
            "GuildSiegeDataIndex": 1
        },
        {
            "Index": 13,
            "Type": 1,
            "GuildSiegeDataIndex": 6
        },
        {
            "Index": 14,
            "Type": 1,
            "GuildSiegeDataIndex": 8
        },
        {
            "Index": 15
        }
    ],
    "hash": "5xAkDCH14sp2D0uL/6EQG5/3HH42dp2pF5bCpe/b9hY="
}