{
  "m_GameObject": {
    "m_FileID": 0,
    "m_PathID": 0
  },
  "m_Enabled": 1,
  "m_Script": {
    "m_FileID": 0,
    "m_PathID": 4618677692367072574
  },
  "m_Name": "SkillCam_3015004_2",
  "camCfg1": {
    "LookMonvTime": 0.1,
    "LookEffectTime": 0.7,
    "LookMonvBodyOffset": {
      "x": 3.7,
      "y": 0.38,
      "z": -1.76
    },
    "LookEffectBodyOffset": {
      "x": 3.7,
      "y": 0.38,
      "z": -1.76
    },
    "LookHitBodyOffset": {
      "x": 3.6,
      "y": 1.05,
      "z": -3.0
    },
    "LookMonvAimOffset": {
      "x": 2.0,
      "y": 0.22,
      "z": 0.0
    },
    "LookEffectAimOffset": {
      "x": 2.0,
      "y": 0.22,
      "z": 0.0
    },
    "LookHitAimOffset": {
      "x": 1.5,
      "y": 0.37,
      "z": 0.0
    },
    "IsFollowEffect": 0,
    "IsFollowHit": 0,
    "TweenTime": 2.0,
    "blendTime": 1.0
  },
  "camCfg2": {
    "LookMonvTime": 0.1,
    "LookEffectTime": 0.7,
    "LookMonvBodyOffset": {
      "x": 3.13,
      "y": 0.31,
      "z": -2.6
    },
    "LookEffectBodyOffset": {
      "x": 3.13,
      "y": 0.31,
      "z": -2.6
    },
    "LookHitBodyOffset": {
      "x": 3.6,
      "y": 1.05,
      "z": -3.0
    },
    "LookMonvAimOffset": {
      "x": 1.64,
      "y": 0.07,
      "z": 0.0
    },
    "LookEffectAimOffset": {
      "x": 1.64,
      "y": 0.07,
      "z": 0.0
    },
    "LookHitAimOffset": {
      "x": 1.5,
      "y": 0.37,
      "z": 0.0
    },
    "IsFollowEffect": 0,
    "IsFollowHit": 0,
    "TweenTime": 2.0,
    "blendTime": 1.0
  },
  "camCfg3": {
    "LookMonvTime": 0.1,
    "LookEffectTime": 0.7,
    "LookMonvBodyOffset": {
      "x": 1.52,
      "y": 0.38,
      "z": -4.0
    },
    "LookEffectBodyOffset": {
      "x": 1.52,
      "y": 0.38,
      "z": -4.0
    },
    "LookHitBodyOffset": {
      "x": 2.06,
      "y": 1.05,
      "z": -4.0
    },
    "LookMonvAimOffset": {
      "x": 1.17,
      "y": 0.22,
      "z": 0.0
    },
    "LookEffectAimOffset": {
      "x": 1.17,
      "y": 0.22,
      "z": 0.0
    },
    "LookHitAimOffset": {
      "x": 1.5,
      "y": 0.37,
      "z": 0.0
    },
    "IsFollowEffect": 0,
    "IsFollowHit": 0,
    "TweenTime": 2.0,
    "blendTime": 1.0
  }
}